pynterface/__init__.py
pynterface/input.py
pynterface/loading.py
pynterface/menu.py
pynterface/printing.py
pynterface/style.py
pynterface-0.2.4.dist-info/LICENSE
pynterface-0.2.4.dist-info/METADATA
pynterface-0.2.4.dist-info/WHEEL
pynterface-0.2.4.dist-info/top_level.txt
pynterface-0.2.4.dist-info/RECORD
