Metadata-Version: 2.1
Name: pynterface
Version: 0.2.4
Summary: Terminal-Based Printing Tools!
Author: Vivaan Singhvi
Author-email: singhvi.vivaan@gmail.com
License: MIT
Project-URL: Documentation, https://pynterface.readthedocs.io/en/latest/
Requires-Python: >=3.8
License-File: LICENSE
